exceptor_magic/__init__.py
exceptor_magic-0.2.dist-info/LICENSE
exceptor_magic-0.2.dist-info/WHEEL
exceptor_magic-0.2.dist-info/METADATA
exceptor_magic-0.2.dist-info/RECORD
