Metadata-Version: 2.1
Name: exceptor_magic
Version: 0.2
Summary: magic to alert on fail or success
Home-page: UNKNOWN
License: UNKNOWN
Author: sam shleifer
Author-email: sshleifer@gmail.com
Classifier: License :: OSI Approved :: MIT License
